{"id":2354415,"statsId":87069,"significance":"Lower bracket final","team1":{"name":"allStars","id":11240},"team2":{"name":"VAMOSTARS","id":11526},"winnerTeam":{"name":"allStars","id":11240},"date":1644674400000,"format":{"type":"bo3","location":"LAN"},"event":{"name":"Jaxi League Elite Series 2022 Finals","id":6387},"maps":[{"name":"de_vertigo","result":{"team1TotalRounds":16,"team2TotalRounds":5,"halfResults":[{"team1Rounds":11,"team2Rounds":4},{"team1Rounds":5,"team2Rounds":1}]},"statsId":133766},{"name":"de_mirage","result":{"team1TotalRounds":19,"team2TotalRounds":16,"halfResults":[{"team1Rounds":4,"team2Rounds":11},{"team1Rounds":11,"team2Rounds":4},{"team1Rounds":4,"team2Rounds":1}]},"statsId":133770},{"name":"de_nuke"}],"players":{"team1":[{"name":"Blytz","id":12945},{"name":"xAHEN","id":21212},{"name":"l0rd-dll","id":20826},{"name":"cox","id":11112},{"name":"ERSIN","id":21213}],"team2":[{"name":"markk","id":15785},{"name":"CHANKY","id":16548},{"name":"habibi","id":19826},{"name":"RENNE","id":20168},{"name":"ReuS","id":21781}]},"streams":[],"status":"Over","hasScorebot":false,"playerOfTheMatch":{"name":"l0rd-dll","id":20826},"headToHead":[],"vetoes":[{"team":{"name":"VAMOSTARS","id":11526},"map":"de_inferno","type":"removed"},{"team":{"name":"allStars","id":11240},"map":"de_dust2","type":"removed"},{"team":{"name":"VAMOSTARS","id":11526},"map":"de_vertigo","type":"picked"},{"team":{"name":"allStars","id":11240},"map":"de_mirage","type":"picked"},{"team":{"name":"VAMOSTARS","id":11526},"map":"de_overpass","type":"removed"},{"team":{"name":"allStars","id":11240},"map":"de_ancient","type":"removed"},{"map":"de_nuke","type":"leftover"}],"highlights":[],"demos":[{"name":"GOTV Demo","link":"/download/demo/69997"},{"name":"jaxi (Map 1 - Vertigo)","link":"https://www.youtube.com/embed/l2zfZrog_I8?autoplay=1&start=1812"},{"name":"jaxi (Map 2 - Mirage)","link":"https://www.youtube.com/embed/l2zfZrog_I8?autoplay=1&start=5147"}],"odds":[]}