{"id":2354546,"statsId":87839,"significance":"Group B","team1":{"name":"Outsiders","id":11595},"team2":{"name":"FaZe","id":6667},"winnerTeam":{"name":"Outsiders","id":11595},"date":1647541800000,"format":{"type":"bo3","location":"LAN"},"event":{"name":"ESL Pro League Season 15","id":6137},"maps":[{"name":"de_inferno","result":{"team1TotalRounds":16,"team2TotalRounds":8,"halfResults":[{"team1Rounds":7,"team2Rounds":8},{"team1Rounds":9,"team2Rounds":0}]},"statsId":135502},{"name":"de_dust2","result":{"team1TotalRounds":22,"team2TotalRounds":18,"halfResults":[{"team1Rounds":9,"team2Rounds":6},{"team1Rounds":6,"team2Rounds":9},{"team1Rounds":7,"team2Rounds":3}]},"statsId":135506},{"name":"de_mirage"}],"players":{"team1":[{"name":"buster","id":11942},{"name":"Qikert","id":13239},{"name":"Jame","id":13776},{"name":"FL1T","id":12732},{"name":"YEKINDAR","id":13915}],"team2":[{"name":"rain","id":8183},{"name":"Twistzz","id":10394},{"name":"broky","id":18053},{"name":"ropz","id":11816},{"name":"karrigan","id":429}]},"streams":[],"status":"Over","hasScorebot":false,"playerOfTheMatch":{"name":"YEKINDAR","id":13915},"headToHead":[{"date":1635876123000,"map":"ovp","winner":{"name":"Virtus.pro","id":5378},"event":{"name":"PGL Major Stockholm 2021","id":4866},"result":"16 - 11"},{"date":1635876123000,"map":"anc","winner":{"name":"Virtus.pro","id":5378},"event":{"name":"PGL Major Stockholm 2021","id":4866},"result":"16 - 14"},{"date":1635876123000,"map":"inf","winner":{"name":"FaZe","id":6667},"event":{"name":"PGL Major Stockholm 2021","id":4866},"result":"13 - 16"},{"date":1635339361000,"map":"anc","winner":{"name":"FaZe","id":6667},"event":{"name":"PGL Major Stockholm 2021 Challengers Stage","id":6207},"result":"6 - 16"},{"date":1635339361000,"map":"mrg","winner":{"name":"FaZe","id":6667},"event":{"name":"PGL Major Stockholm 2021 Challengers Stage","id":6207},"result":"14 - 16"},{"date":1631117905000,"map":"d2","winner":{"name":"Virtus.pro","id":5378},"event":{"name":"Pinnacle Fall Series 1","id":6101},"result":"16 - 11"},{"date":1631117905000,"map":"inf","winner":{"name":"FaZe","id":6667},"event":{"name":"Pinnacle Fall Series 1","id":6101},"result":"8 - 16"},{"date":1631117905000,"map":"mrg","winner":{"name":"Virtus.pro","id":5378},"event":{"name":"Pinnacle Fall Series 1","id":6101},"result":"16 - 2"},{"date":1619700605000,"map":"trn","winner":{"name":"Virtus.pro","id":5378},"event":{"name":"DreamHack Masters Spring 2021","id":5728},"result":"16 - 13"}],"vetoes":[{"team":{"name":"FaZe","id":6667},"map":"de_vertigo","type":"removed"},{"team":{"name":"Outsiders","id":11595},"map":"de_nuke","type":"removed"},{"team":{"name":"FaZe","id":6667},"map":"de_inferno","type":"picked"},{"team":{"name":"Outsiders","id":11595},"map":"de_dust2","type":"picked"},{"team":{"name":"FaZe","id":6667},"map":"de_ancient","type":"removed"},{"team":{"name":"Outsiders","id":11595},"map":"de_overpass","type":"removed"},{"map":"de_mirage","type":"leftover"}],"highlights":[{"link":"https://clips.twitch.tv/embed?clip=LazyInquisitiveHyenaBIRB-Vy7nU-KPIZ_M2Tce&autoplay=true&parent=www.hltv.org","title":"M1 | Twistzz's 1vs3 clutch attempt (CT - post-plant) is denied by the final T (YEKINDAR) to secure the map victory for Outsiders"},{"link":"https://clips.twitch.tv/embed?clip=SpicyConcernedArugulaSaltBae-jE71F8Caj1foldSF&autoplay=true&parent=www.hltv.org","title":"M2 | Jame - 3 Glock HS kills on the bombsite A bomb plant defense (2vs3 situation - pistol round)"},{"link":"https://clips.twitch.tv/embed?clip=GoodPerfectCocoaFloof-WIMHGhFDYN4HFyAy&autoplay=true&parent=www.hltv.org","title":"M2 | ropz (CT) wins the 1vs2 situation (frag wise) but fails to secure the round win as the bomb timer is not in his favor"}],"demos":[{"name":"GOTV Demo","link":"/download/demo/70769"},{"name":"ESL TV (Map 1 - Inferno)","link":"https://player.twitch.tv/?video=v1428208581&autoplay=true&t=7h53m3s&parent=www.hltv.org"},{"name":"ESL TV (Map 2 - Dust 2)","link":"https://player.twitch.tv/?video=v1428208581&autoplay=true&t=9h11m43s&parent=www.hltv.org"}],"odds":[]}