{"id":2354062,"statsId":86762,"significance":"Swiss round 4 (teams with a 2-1 record). Winner advances to Pinnacle Winter Series 1.","team1":{"name":"GamerLegion","id":9928},"team2":{"name":"Unique","id":9287},"winnerTeam":{"name":"Unique","id":9287},"date":1642687200000,"format":{"type":"bo3","location":"Online"},"event":{"name":"Pinnacle Winter Series 1 Regionals","id":6352},"maps":[{"name":"de_inferno","result":{"team1TotalRounds":11,"team2TotalRounds":16,"halfResults":[{"team1Rounds":4,"team2Rounds":11},{"team1Rounds":7,"team2Rounds":5}]},"statsId":132953},{"name":"de_mirage","result":{"team1TotalRounds":16,"team2TotalRounds":13,"halfResults":[{"team1Rounds":7,"team2Rounds":8},{"team1Rounds":9,"team2Rounds":5}]},"statsId":132959},{"name":"de_ancient","result":{"team1TotalRounds":10,"team2TotalRounds":16,"halfResults":[{"team1Rounds":5,"team2Rounds":10},{"team1Rounds":5,"team2Rounds":6}]},"statsId":132966}],"players":{"team1":[{"name":"RuStY","id":10784},{"name":"eraa","id":16487},{"name":"isak","id":17937},{"name":"Zero","id":8413},{"name":"iM","id":14759}],"team2":[{"name":"ice","id":17792},{"name":"smiley","id":17793},{"name":"dukefissura","id":19823},{"name":"sorrow","id":19967},{"name":"w1nt3r","id":14359}]},"streams":[],"status":"Over","hasScorebot":false,"playerOfTheMatch":{"name":"dukefissura","id":19823},"headToHead":[{"date":1621262954000,"map":"inf","winner":{"name":"GamerLegion","id":9928},"event":{"name":"Spring Sweet Spring 2 Regionals","id":5915},"result":"16 - 7"},{"date":1621262954000,"map":"ovp","winner":{"name":"GamerLegion","id":9928},"event":{"name":"Spring Sweet Spring 2 Regionals","id":5915},"result":"16 - 7"}],"vetoes":[{"team":{"name":"Unique","id":9287},"map":"de_nuke","type":"removed"},{"team":{"name":"GamerLegion","id":9928},"map":"de_dust2","type":"removed"},{"team":{"name":"Unique","id":9287},"map":"de_inferno","type":"picked"},{"team":{"name":"GamerLegion","id":9928},"map":"de_mirage","type":"picked"},{"team":{"name":"Unique","id":9287},"map":"de_vertigo","type":"removed"},{"team":{"name":"GamerLegion","id":9928},"map":"de_overpass","type":"removed"},{"map":"de_ancient","type":"leftover"}],"highlights":[{"link":"https://clips.twitch.tv/embed?clip=SpotlessArtsyGullDancingBaby-NXUJ1qkXMWlaEXMs&autoplay=true&parent=www.hltv.org","title":"M1 | smiley - 1vs2 clutch (T - pre-plant situation)"},{"link":"https://clips.twitch.tv/embed?clip=SpunkyInnocentStorkHassanChop-PTaCnafBgz85cKDR&autoplay=true&parent=www.hltv.org","title":"M2 | RuStY - 1vs2 clutch (CT - post-plant situation)"},{"link":"https://clips.twitch.tv/embed?clip=SleepyFrozenGalagoDatSheffy-s7QadSCj4P8hxAHS&autoplay=true&parent=www.hltv.org","title":"M2 | Zero - 3 M4A1-S kills on the bombsite A retake (2vs3 post-plant situation) to secure the map victory for GamerLegion"},{"link":"https://clips.twitch.tv/embed?clip=ClearFitPoultryFreakinStinkin-g2c1GMXbSspk05ja&autoplay=true&parent=www.hltv.org","title":"M3 | w1nt3r - 4 AK kills (3 HS) on the defense (clean round - vs upgraded pistols)"},{"link":"https://clips.twitch.tv/embed?clip=WildGrossClipzDatBoi-tzW1CU2hUUvCWVbZ&autoplay=true&parent=www.hltv.org","title":"M3 | RuStY - 1vs2 clutch (T - bomb planted after 1 clutch kill)"},{"link":"https://clips.twitch.tv/embed?clip=AnimatedTallGullSmoocherZ-ab-ZkozA7PWuaXn0&autoplay=true&parent=www.hltv.org","title":"M3 | dukefissura - 4 AK kills (3 HS) on the bombsite B defense"}],"demos":[{"name":"GOTV Demo","link":"/download/demo/69692"},{"name":"Champion of Champions (Map 1 - Inferno)","link":"https://player.twitch.tv/?video=v1269701916&autoplay=true&t=6h37m10s&parent=www.hltv.org"},{"name":"Champion of Champions (Map 2 - Mirage)","link":"https://player.twitch.tv/?video=v1269701916&autoplay=true&t=7h44m46s&parent=www.hltv.org"},{"name":"Champion of Champions (Map 3 - Ancient)","link":"https://player.twitch.tv/?video=v1269701916&autoplay=true&t=9h2m29s&parent=www.hltv.org"}],"odds":[]}